{"metadata": {"dbt_schema_version": "https://schemas.getdbt.com/dbt/run-results/v6.json", "dbt_version": "1.11.6", "generated_at": "2026-02-25T07:48:06.902645Z", "invocation_id": "b26a0055-1e39-4e36-b624-ebfc432355c0", "invocation_started_at": "2026-02-25T07:47:50.476708Z", "env": {}}, "results": [{"status": "success", "timing": [{"name": "compile", "started_at": "2026-02-25T07:48:03.484708Z", "completed_at": "2026-02-25T07:48:03.498541Z"}, {"name": "execute", "started_at": "2026-02-25T07:48:03.499315Z", "completed_at": "2026-02-25T07:48:06.883241Z"}], "thread_id": "Thread-1 (worker)", "execution_time": 3.404683828353882, "adapter_response": {"_message": "CREATE TABLE (7.6k rows, 5.5 GiB processed)", "code": "CREATE TABLE", "rows_affected": 7617, "bytes_processed": 5864102829, "bytes_billed": 5864685568, "location": "US", "project_id": "electric-cosine-485318-f9", "job_id": "a9737764-2060-4a24-b1d5-e545b1150cb9", "slot_ms": 80882}, "message": "CREATE TABLE (7.6k rows, 5.5 GiB processed)", "failures": null, "unique_id": "model.taxi_rides_ny.fct_monthly_zone_revenue", "compiled": true, "compiled_code": "\n\nwith trips_data as (\n    select * from `electric-cosine-485318-f9`.`dbt_prod`.`fact_trips`\n)\n\nselect\n    -- revenue grouping\n    pickup_zones.zone as revenue_zone,\n    timestamp_trunc(\n        cast(pickup_datetime as timestamp),\n        month\n    ) as revenue_month,\n    service_type,\n\n    -- revenue calculation\n    sum(fare_amount) as revenue_monthly_fare,\n    sum(extra) as revenue_monthly_extra,\n    sum(mta_tax) as revenue_monthly_mta_tax,\n    sum(tip_amount) as revenue_monthly_tip_amount,\n    sum(tolls_amount) as revenue_monthly_tolls_amount,\n    sum(improvement_surcharge) as revenue_monthly_improvement_surcharge,\n    sum(total_amount) as revenue_monthly_total_amount,\n    sum(congestion_surcharge) as revenue_monthly_congestion_surcharge,\n\n    -- count\n    count(tripid) as total_monthly_trips,\n    avg(passenger_count) as avg_monthly_passenger_count,\n    avg(trip_distance) as avg_monthly_trip_distance\n\nfrom trips_data\ninner join `electric-cosine-485318-f9`.`dbt_prod`.`dim_zones` as pickup_zones\n    on trips_data.pickup_locationid = pickup_zones.locationid\ngroup by 1, 2, 3", "relation_name": "`electric-cosine-485318-f9`.`dbt_prod`.`fct_monthly_zone_revenue`", "batch_results": null}], "elapsed_time": 3.8602843284606934, "args": {"warn_error_options": {"error": [], "warn": [], "silence": []}, "validate_macro_args": false, "state_modified_compare_more_unrendered_values": false, "populate_cache": true, "log_path": "/home/ahmadavar/data-engineering-zoomcamp-2026/04-analytics-engineering/logs", "require_all_warnings_handled_by_warn_error": false, "show": false, "show_resource_report": false, "favor_state": false, "log_format_file": "debug", "require_generic_test_arguments_property": true, "defer": false, "printer_width": 80, "require_batched_execution_for_custom_microbatch_strategy": false, "empty": false, "print": true, "vars": {}, "export_saved_queries": false, "use_fast_test_edges": false, "require_explicit_package_overrides_for_builtin_materializations": true, "log_level_file": "debug", "require_nested_cumulative_type_params": false, "require_unique_project_resource_names": false, "state_modified_compare_vars": false, "profiles_dir": "/home/ahmadavar/.dbt", "partial_parse": true, "log_file_max_bytes": 10485760, "version_check": true, "exclude_resource_types": [], "project_dir": "/home/ahmadavar/data-engineering-zoomcamp-2026/04-analytics-engineering", "select": ["fct_monthly_zone_revenue"], "macro_debugging": false, "write_json": true, "source_freshness_run_project_hooks": true, "indirect_selection": "eager", "strict_mode": false, "show_all_deprecations": false, "require_yaml_configuration_for_mf_time_spines": false, "use_colors": true, "upload_to_artifacts_ingest_api": false, "introspect": true, "partial_parse_file_diff": true, "static_parser": true, "use_colors_file": true, "which": "build", "include_saved_query": false, "target": "prod", "invocation_command": "dbt build --target prod --select fct_monthly_zone_revenue", "send_anonymous_usage_stats": true, "quiet": false, "require_resource_names_without_spaces": true, "skip_nodes_if_on_run_start_fails": false, "resource_types": [], "log_format": "default", "log_level": "info", "exclude": [], "require_ref_searches_node_package_before_root": false, "cache_selected_only": false}}